{
  "total_sentencas": 298,
  "dados": [
    {
      "sentenca": "Documento id 1821189655 - Sentença Tipo D",
      "label": "OUTROS"
    },
    {
      "sentenca": "PODER JUDICIÁRIO",
      "label": "OUTROS"
    },
    {
      "sentenca": "JUSTIÇA FEDERAL",
      "label": "OUTROS"
    },
    {
      "sentenca": "Subseção Judiciária de Altamira-PA",
      "label": "OUTROS"
    },
    {
      "sentenca": "Vara Federal Cível e Criminal da SSJ de Altamira-PA",
      "label": "OUTROS"
    },
    {
      "sentenca": "SENTENÇA TIPO \"D\"",
      "label": "RELATORIO"
    },
    {
      "sentenca": "PROCESSO: 0000563-90.2019.4.01.3903",
      "label": "RELATORIO"
    },
    {
      "sentenca": "CLASSE: AÇÃO PENAL - PROCEDIMENTO ORDINÁRIO (283)",
      "label": "RELATORIO"
    },
    {
      "sentenca": "POLO ATIVO: Ministério Público Federal (Procuradoria)",
      "label": "RELATORIO"
    },
    {
      "sentenca": "POLO PASSIVO:DIRCEU DA LUZ e outros",
      "label": "RELATORIO"
    },
    {
      "sentenca": "REPRESENTANTES POLO PASSIVO: INGRYD OLIVEIRA COUTO - PA14834-B e IULLE OLIVEIRA DOS SANTOS - PA28537",
      "label": "RELATORIO"
    },
    {
      "sentenca": "SENTENÇA",
      "label": "RELATORIO"
    },
    {
      "sentenca": "1-RELATÓRIO",
      "label": "RELATORIO"
    },
    {
      "sentenca": "O MPF denunciou DIRCEU DA LUZ como incurso, por duas vezes e em concurso formal, na forma do artigo 70 do Código Penal, nos artigos 149, caput, 297, § 4º, todos do Código Penal, e EDIVAL DA LUZ como incurso, por cinco vezes, nos delitos do artigo 149 e 297, § 4º, na forma do artigo 69, todos do Código Penal.",
      "label": "RELATORIO"
    },
    {
      "sentenca": "Narra a denúncia que, entre 17/4/2017 e 15/5/2019, no Sítio Castanhal, situado no Travessão Dois e Meio, no Município de Medicilândia/PA, DIRCEU DA LUZ teria reduzido dois trabalhadores à condição análoga à de escravo, por submetê-los a condições degradantes de trabalho.",
      "label": "DOS_FATOS"
    },
    {
      "sentenca": "Neste mesmo período, no sítio Carlos Böecker, situado no Travessão Dois e Meio, no Município de Medicilândia/PA, EDIVAL DA LUZ teria reduzido cinco trabalhadores à condição análoga à de escravo, por submetê-los a condições degradantes de trabalho.",
      "label": "DOS_FATOS"
    },
    {
      "sentenca": "A denúncia foi recebida em 20 de agosto de 2019 (ID 227640350, p. 5-6).",
      "label": "RELATORIO"
    },
    {
      "sentenca": "Certificada pela oficiala de justiça a não localização do sr. DIRCEU DA LUZ (ID 781568966).",
      "label": "RELATORIO"
    },
    {
      "sentenca": "Citado o acusado EDIVAL DA LUZ (ID 954261180), juntou procuração (ID 944860685) e apresentou resposta à acusação, alegando que houve contrato de empreitada e a não configuração do crime, considerando ter havido contrato de empreitada, seja por ausência de restrição à locomoção, seja por ausência de condições degradantes de trabalho a ponto de configuração de ilícito penal (ID 953489684).",
      "label": "RELATORIO"
    },
    {
      "sentenca": "Num. 1821189655 - Pág. 1",
      "label": "OUTROS"
    },
    {
      "sentenca": "Assinado eletronicamente por: MICHAEL PROCOPIO RIBEIRO ALVES AVELAR - 20/09/2023 15:22:25",
      "label": "OUTROS"
    },
    {
      "sentenca": "https://pje1g.trf1.jus.br:443/consultapublica/Processo/ConsultaDocumento/listView.seam?x=23091816304471000001796688347",
      "label": "OUTROS"
    },
    {
      "sentenca": "Número do documento: 23091816304471000001796688347Documento id 1821189655 - Sentença Tipo D",
      "label": "OUTROS"
    },
    {
      "sentenca": "Foi, então, citado o acusado DIRCEU DA LUZ (ID 1286081769), que juntou procuração (ID 1295521765) e apresentou resposta à acusação, aduzindo que não se configurou o delito, não tendo ocorrido restrição ao direito de locomoção e por não ter sido provado que a água era imprópria para consumo humano (ID 1295521786).",
      "label": "RELATORIO"
    },
    {
      "sentenca": "O MPF manifestou-se contrariamente à absolvição sumária (ID 1376467765).",
      "label": "RELATORIO"
    },
    {
      "sentenca": "Foi, então, confirmado o recebimento da denúncia e designada audiência de instrução de julgamento (ID 1496711352).",
      "label": "RELATORIO"
    },
    {
      "sentenca": "Então, antes de realizada a instrução de julgamento, o MPF pediu a juntada de novos documentos, oriundos Divisão de Fiscalização para Erradicação do Trabalho em Condições Análogas à de Escravo, a que não teria tido acesso anteriormente (ID 1721689471).",
      "label": "RELATORIO"
    },
    {
      "sentenca": "Realizada audiência de instrução de julgamento, foram ouvidas testemunhas e, em continuação, ouvidas as testemunhas restantes e interrogados os réus.",
      "label": "RELATORIO"
    },
    {
      "sentenca": "Em suas alegações finais orais, o MPF disse que, para o crime do artigo 149 do CP, não se exige a relação de emprego, mas apenas de trabalho.",
      "label": "RELATORIO"
    },
    {
      "sentenca": "Não se exige relação de emprego, de modo que a discussão de existência ou não de empreitada não desconstitui o delito narrado.",
      "label": "RELATORIO"
    },
    {
      "sentenca": "Disse que as provas indicam a ocorrência do crime do artigo 149 do CP e entende que o outro crime indicado, do artigo 297, deve ser absorvido pelo artigo 149 do CP.",
      "label": "RELATORIO"
    },
    {
      "sentenca": "Quanto ao crime de condição análoga à de escravo, pugna pela condenação nos termos da denúncia.",
      "label": "RELATORIO"
    },
    {
      "sentenca": "De fato, não houve restrição de liberdade.",
      "label": "RELATORIO"
    },
    {
      "sentenca": "Ocorre que o dispositivo prevê escravidão contemporânea, de modo que não se exige restrição de liberdade, com cadeado na porteira, vigilância ostensiva.",
      "label": "RELATORIO"
    },
    {
      "sentenca": "É possível a configuração mesmo sem restrição de liberdade ou vigilância armada, configurando-se o crime se houver condições degradantes, aqueles que não são apenas ruins, mas violadoras da dignidade da pessoa humana, visando-se a evitar a objetificação das pessoas, como se fossem meros recursos para consecução das atividades econômicas.",
      "label": "RELATORIO"
    },
    {
      "sentenca": "Consta do relatório feito pela equipe de diligência, de ID 227623941, a partir da página 8, que não houve acatamento integral de tudo o que os empregados disseram, houve uma ponderação.",
      "label": "RELATORIO"
    },
    {
      "sentenca": "Encontraram inconsistências quanto aos períodos e, desse modo, consideraram um período menor, ID 227623944, conforme página 5.",
      "label": "RELATORIO"
    },
    {
      "sentenca": "As fotos e o relatório demonstram onde moraram, o barraco de lona.",
      "label": "RELATORIO"
    },
    {
      "sentenca": "Ainda que se possa alegar que não havia água tratada no Município, mas não se pode usar do igarapé sem nenhum tratamento.",
      "label": "RELATORIO"
    },
    {
      "sentenca": "No entanto, não se trata apenas da água, mas um conjunto de fatores.",
      "label": "RELATORIO"
    },
    {
      "sentenca": "O relatório aponta que 3 dos trabalhadores estavam apenas há 3 dias, mas os outros estavam há anos na propriedade.",
      "label": "RELATORIO"
    },
    {
      "sentenca": "No entanto, mesmo esses 3 teriam se mudado em definitivo, para morarem no local, razão pela qual se deve considerar consumado do delito, ainda que por curto período quanto aos 3.",
      "label": "RELATORIO"
    },
    {
      "sentenca": "O que consta do relatório e não foi desconstituído pelas testemunhas é que alguns trabalhadores ficaram lá por anos.",
      "label": "RELATORIO"
    },
    {
      "sentenca": "Não há provas que possam desconstituir esse fato e o depoimento do auditor fiscal do trabalho foi realizado em juízo e, ao acompanhar diligências, o MPF não tem notado abusos.",
      "label": "RELATORIO"
    },
    {
      "sentenca": "Pelo relatado, seria possível a prisão em flagrante e, em deferência à situação familiar, ao que parece, não foi feito.",
      "label": "RELATORIO"
    },
    {
      "sentenca": "As diligências foram realizadas na presença de membro da DPU, de modo que não entende haver coação quanto às declarações feitas e à assinatura do termo de ajuste de conduta.",
      "label": "RELATORIO"
    },
    {
      "sentenca": "Sobre os elementos juntados posteriormente pelo auditor fiscal do trabalho, confirmam o seu depoimento e, dada a rotineira atividade de fiscalização, há de se ponderar não ser possível se recordar de todos os fatos.",
      "label": "RELATORIO"
    },
    {
      "sentenca": "As demais fotos da diligência demonstram uma situação degradante e, pelo que consta nos autos, não se pode concluir ter sido uma emboscada ou armadilha a prejudicar os acusados.",
      "label": "RELATORIO"
    },
    {
      "sentenca": "Num. 1821189655 - Pág. 2",
      "label": "OUTROS"
    },
    {
      "sentenca": "Assinado eletronicamente por: MICHAEL PROCOPIO RIBEIRO ALVES AVELAR - 20/09/2023 15:22:25",
      "label": "OUTROS"
    },
    {
      "sentenca": "https://pje1g.trf1.jus.br:443/consultapublica/Processo/ConsultaDocumento/listView.seam?x=23091816304471000001796688347",
      "label": "OUTROS"
    },
    {
      "sentenca": "Número do documento: 23091816304471000001796688347Documento id 1821189655 - Sentença Tipo D",
      "label": "OUTROS"
    },
    {
      "sentenca": "Também não é possível extrair dos autos uma combinação entre trabalhadores e servidores públicos.",
      "label": "RELATORIO"
    },
    {
      "sentenca": "O aparato de segurança é proporcional, dada a possibilidade de pessoas violentas, o que não foi o caso dos réus, serem fiscalizados.",
      "label": "RELATORIO"
    },
    {
      "sentenca": "Apesar da alegação de empreitada, foi reconhecido o vínculo de emprego pelo termo de ajuste de conduta.",
      "label": "RELATORIO"
    },
    {
      "sentenca": "Pede a condenação pelo delito do artigo 149, na forma do artigo 70 do CP.",
      "label": "RELATORIO"
    },
    {
      "sentenca": "Os réus em alegações finais por meio de memorial (ID 1766193085), aduziram em síntese: que não restou provado o crime de redução à condição análoga de escravo; que ficou provado que os trabalhadores eram empreiteiros; prescrição dos crimes descritos nos art. 203, 149 e 297, § 4º, do CP.",
      "label": "RELATORIO"
    },
    {
      "sentenca": "Fundamento e decido.",
      "label": "FUNDAMENTACAO"
    },
    {
      "sentenca": "2-FUNDAMENTAÇÃO",
      "label": "FUNDAMENTACAO"
    },
    {
      "sentenca": "DA PRESCRIÇÃO DA PRETENSÃO PUNITIVA.",
      "label": "FUNDAMENTACAO"
    },
    {
      "sentenca": "No caso, considerando as penas máximas em abstrato previstas nos delitos imputados, ou seja, art. 149, pena de 8 anos, e 297, § 4º, pena de 6 anos, não ocorreu prescrição da pretensão punitiva, uma vez que a denúncia foi recebida em 20.08.2019.",
      "label": "FUNDAMENTACAO"
    },
    {
      "sentenca": "Por conseguinte, não superou o lapso temporal previsto no art. 109, III, do CP.",
      "label": "FUNDAMENTACAO"
    },
    {
      "sentenca": "Por fim, não foi imputado aos réus o delito descrito no art. 203,CP.",
      "label": "FUNDAMENTACAO"
    },
    {
      "sentenca": "Assim, rejeito a presente prejudicial de prescrição.",
      "label": "FUNDAMENTACAO"
    },
    {
      "sentenca": "DO CRIME DO ART. 149, CP em relação aos trabalhadores resgatados",
      "label": "FUNDAMENTACAO"
    },
    {
      "sentenca": "O tipo penal do artigo 149 é traz a conduta de reduzir alguém a condição análoga a de escravo, elencando, exaustivamente, as formas de se realizar esse núcleo do tipo.",
      "label": "FUNDAMENTACAO"
    },
    {
      "sentenca": "Assim, o delito resta configurado se constatada qualquer uma das seguintes circunstâncias: i) submissão de alguém a trabalhos forçados ou a jornada exaustiva; ii) sujeição de alguém a condições degradantes de trabalho; iii) restrição à locomoção de alguém em razão de dívida contraída com o empregador ou preposto.",
      "label": "FUNDAMENTACAO"
    },
    {
      "sentenca": "Fixadas essas premissas, observo que a materialidade delitiva do crime do artigo 149 do Código Penal restou devidamente comprovada nos autos, pelos elementos probatórios a seguir descritos.",
      "label": "FUNDAMENTACAO"
    },
    {
      "sentenca": "Narra a inicial acusatória que o acusado DIRCEU DA LUZ teria, entre 17/4/2017 e 15/5/2019, no Sítio Castanhal, no Travessão Dois e Meio, no Município de Medicilândia/PA, de forma livre e consciente, reduzido 2 trabalhadores à condição análoga à de escravo.",
      "label": "FUNDAMENTACAO"
    },
    {
      "sentenca": "Narra, ainda, que o acusado EDIVAL DA LUZ teria, entre 17/4/2017 e 15/5/2019, no Sítio Carlos Böecker, no Travessão Dois e Meio, no Município de Medicilândia/PA, de forma livre e consciente, reduzido 5 trabalhadores à condição análoga à de escravo.",
      "label": "FUNDAMENTACAO"
    },
    {
      "sentenca": "Além disso, os dois denunciados, de maneira dolosa, teriam omitido da CTPS dos empregados a remuneração e a vigência do contrato de prestação de serviços, incorrendo no crime previsto no artigo 297, § 4º, do CP.",
      "label": "FUNDAMENTACAO"
    },
    {
      "sentenca": "Num. 1821189655 - Pág. 3",
      "label": "OUTROS"
    },
    {
      "sentenca": "Assinado eletronicamente por: MICHAEL PROCOPIO RIBEIRO ALVES AVELAR - 20/09/2023 15:22:25",
      "label": "OUTROS"
    },
    {
      "sentenca": "https://pje1g.trf1.jus.br:443/consultapublica/Processo/ConsultaDocumento/listView.seam?x=23091816304471000001796688347",
      "label": "OUTROS"
    },
    {
      "sentenca": "Número do documento: 23091816304471000001796688347Documento id 1821189655 - Sentença Tipo D",
      "label": "OUTROS"
    },
    {
      "sentenca": "A versão acusatória é de que, entre os dias 14 a 18 de abril de 2017, o Grupo Especial Interinstitucional de Fiscalização Móvel (GEIFM) teria realizado diligências no Município de Medicilândia/PA, ocasião em que inspecionaram o Sítio Castanhal e Sítio Carlos Böecker, que pertenceriam, respectivamente, a DIRCEU DA LAZ e a EDIVAL DA LUZ.",
      "label": "FUNDAMENTACAO"
    },
    {
      "sentenca": "No Sítio Castanhal, de responsabilidade de DIRCEU DA LUZ, teriam sido resgatados os trabalhadores, Luiz Carlos Barros Ferraz e Ogleido Feliz de Oliveira, além de terem sido detectadas as seguintes condições degradantes de trabalho: 1) trabalhadores não possuíam CTPS anotada;2) ausência de controle da jornada de trabalho;3) ausência de realização de exames médicos admissionais; 4) fornecimento de alimentação precária pelo empregador, sendo descontados valores acima dos limites legais dos trabalhadores pela alimentação fornecida;5) preparo e acondicionamento dos alimentos de forma inapropriada, hão higiênica;6) ausência de instalações sanitárias.",
      "label": "FUNDAMENTACAO"
    },
    {
      "sentenca": "sendo os trabalhadores obrigados a realizar suas necessidades fisiológicas no mato, correndo risco de picadas de animais peçonhentos;?) não fornecimento dos equipamentos de proteção individual;8) não fornecimento das ferramentas necessárias para desenvolvimento das atividades, sendo descontados valores a título de ferramentas quando eram fornecidas;9) ausência de local adequado para moradia, sendo que havia trabalhador morando em construção de madeira, com frestas que permitiam a passagem de animas, sem água potável e coberta de lona, em razão de que algumas telhas estavam quebradas;10) ausência de local para acondicionamento de alimentação e ausência de local adequado para preparo de refeições;11) a água consumida pelos trabalhadores para beber e preparar as refeições era retirada de um igarapé no meio do mato;12) o local para banho era no meio do mato em um igarapé;13) não fornecimento de materiais de primeiros socorros;14) ausência de fornecimento de qualquer meio de transporte para deslocar trabalhador acidentado ou picado por animais peçonhentos.",
      "label": "FUNDAMENTACAO"
    },
    {
      "sentenca": "Já no Sítio Carlos Böecker, de responsabilidade de EDIVAL DA LUZ, teriam sido resgatados os trabalhadores, José Maria Rocha Gomes, Isaqueu Oliveira da Silva, Evânio César Moreira, Ronaldo da Silva Costa e Luiz Carlos Trindade dos Santos, além de terem sido detectadas as seguintes condições degradantes de trabalho: 1) ausência de assinatura das CTPS, mesmo com a presença dos requisitos do vínculo de emprego;2) ausência de controle da jornada de trabalho;3) ausência de realização de exames médicos admissionais;4) fornecimento de alimentação precária pelo empregador, sendo descontados valores acima dos limites legais dos trabalhadores; 5) preparo e acondicionamento dos alimentos de forma inapropriada, não higiênica;6) ausência de instalações sanitárias, nas frentes de trabalho, obrigando os empregados a realizarem suas necessidades fisiológicas no mato, correndo risco de picadas de animais peçonhentos;7) instalações sanitárias próximas ao local utilizado como moradia em condições inadequadas;8) não fornecimento dos equipamentos, de proteção individual;9) não fornecimento das ferramentas necessárias para desenvolvimento das atividades, sendo descontados valores a título de ferramentas, quando fornecidas;10) ausência de local adequado para moradia, havendo trabalhador morando em construção de madeira com frestas que permitiam a passagem de animes, sem água potável; 11) presença de barracão de lona utilizado por um dos empregados;12) ausência de local para acondicionamento de alimentação e ausência de local adequado para preparo de refeições;13) a água consumida pelos trabalhadores não era potável, sendo retirada de um riacho e consumida sem tratamento;14) o local utilizado para banho era inadequado;15) não fornecimento de materiais de primeiros socorros;16) ausência de fornecimento de qualquer meio de transporte para deslocar trabalhador acidentado ou picados por animais peçonhentos; »17) aplicação de agrotóxicos sem orientação e sem equipamentos apropriados;18) acondicionamento de vacinas de uso veterinário juntamente com a alimentação dos trabalhadores numa geladeira em uma das edificações.",
      "label": "FUNDAMENTACAO"
    },
    {
      "sentenca": "Com a inicial, foram juntados termos de ajustamento de conduta firmados pelos acusados perante o MPT e a DPU (ID 227584012, p. 13, ID 227584017, ID 227584019, p. 1-7); atas de audiências realizadas no prédio do MPT, (ID 227584019, p. 8-10, ID 227584030, ID 227623931, ID 227623941, p. 1-7); Relatório de Atividades da Operação Altamira (Uruará e Medicilândia), com registros fotográficos das diligências realizadas (ID 227623941, p. 8-10, ID 227623944, 227633395 e ID 227640350, p. 1-2).",
      "label": "FUNDAMENTACAO"
    },
    {
      "sentenca": "Tais circunstâncias foram ilustradas com imagens da situação precária dos trabalhadores, bem como foram corroboradas pelos depoimentos das testemunhas arroladas pela acusação, que afirmaram o seguinte em seus depoimentos:",
      "label": "FUNDAMENTACAO"
    },
    {
      "sentenca": "Ouvido em juízo, Magno Pimenta Riga, auditor fiscal do trabalho, relatou que ocupa o cargo há quase 12 anos.",
      "label": "FUNDAMENTACAO"
    },
    {
      "sentenca": "Sobre o trabalho no grupo de erradicação móvel ao trabalho em condições análogas à de escravo, disse que trabalha há 6 anos, desde 2017, e faz fiscalizações mensalmente.",
      "label": "FUNDAMENTACAO"
    },
    {
      "sentenca": "Sobre o resgate de trabalhadores, disse que existe uma estatística de que o seu grupo especializado o obtém em 30% dos casos.",
      "label": "FUNDAMENTACAO"
    },
    {
      "sentenca": "Sobre o mero descumprimento de normas trabalhistas configurar a situação de escravidão contemporânea, a partir da perspectiva do Ministério do Trabalho, disse não confundir irregularidades com a constatação de trabalho escravo.",
      "label": "FUNDAMENTACAO"
    },
    {
      "sentenca": "Em seu entendimento, irregularidades não configuram trabalho escravo, materializam descumprimento da lei trabalhista, podendo ou não configurar situação de trabalho escravo.",
      "label": "FUNDAMENTACAO"
    },
    {
      "sentenca": "São os mesmos fatos, com implicações jurídicas distintas.",
      "label": "FUNDAMENTACAO"
    },
    {
      "sentenca": "Os mesmos fatos e as mesmas irregularidades podem ser valorados de forma diversa de acordo com o dano ao trabalhador.",
      "label": "FUNDAMENTACAO"
    },
    {
      "sentenca": "Por exemplo, a falta de um armário para o trabalhador não embasaria um resgate, apesar de ser uma irregularidade, dada a previsão da legislação trabalhista.",
      "label": "FUNDAMENTACAO"
    },
    {
      "sentenca": "Agora, estar em um barraco de lona, sem alojamento, pode configurar outra situação, pela falta de condições mínimas de conforto, segurança.",
      "label": "FUNDAMENTACAO"
    },
    {
      "sentenca": "Sobre a fiscalização de 2019, nos sítios dos acusados, disse que se lembra dos sítios e dos acusados presentes, mas não se recorda do nome das propriedades, pois havia transferência de propriedade do pai para eles e o nome estava sendo alterado.",
      "label": "FUNDAMENTACAO"
    },
    {
      "sentenca": "Lembra-se, salvo engano, do resgate de 7 trabalhadores, nas duas propriedades.",
      "label": "FUNDAMENTACAO"
    },
    {
      "sentenca": "Alguns haviam sido contratados por alguns dos irmãos e outros por outro deles, entenderam que havia uma separação da propriedade e da gestão do negócio.",
      "label": "FUNDAMENTACAO"
    },
    {
      "sentenca": "Sobre existência de banheiro, não se recorda em detalhes.",
      "label": "FUNDAMENTACAO"
    },
    {
      "sentenca": "Lembra-se de que estavam alojados em diferentes locais e as condições eram diferentes, um deles estava em um casebre, em um barrado de madeira, onde não havia banheiro.",
      "label": "FUNDAMENTACAO"
    },
    {
      "sentenca": "Outro estava em um barrado similar, coberto por lona.",
      "label": "FUNDAMENTACAO"
    },
    {
      "sentenca": "Alguns, com certeza, não tinham acesso a banheiro naquele momento.",
      "label": "FUNDAMENTACAO"
    },
    {
      "sentenca": "A água fornecida não era potável, havia acesso, mas sem tratamento, conforme normas de potabilidade.",
      "label": "FUNDAMENTACAO"
    },
    {
      "sentenca": "Não se recorda dos detalhes sobre a alimentação.",
      "label": "FUNDAMENTACAO"
    },
    {
      "sentenca": "Sobre a diligência ter sido regular e com oitiva de todas as pessoas, disse que houve regularidade, inclusive DPU participou e houve celebração de termo de ajustamento de conduta, com pagamento das verbas aos trabalhadores.",
      "label": "FUNDAMENTACAO"
    },
    {
      "sentenca": "Houve problema na tramitação administrativa dos autos e foram reconstituídos, sendo remetidos aos trabalhadores.",
      "label": "FUNDAMENTACAO"
    },
    {
      "sentenca": "Sobre a conclusão dos auditores do trabalho, entenderam configurada a situação de redução à condição análoga à de escravo, devido às condições degradantes.",
      "label": "FUNDAMENTACAO"
    },
    {
      "sentenca": "Não havia restrição de liberdade, sem retenção de documentos.",
      "label": "FUNDAMENTACAO"
    },
    {
      "sentenca": "Num. 1821189655 - Pág. 5",
      "label": "OUTROS"
    },
    {
      "sentenca": "Assinado eletronicamente por: MICHAEL PROCOPIO RIBEIRO ALVES AVELAR - 20/09/2023 15:22:25",
      "label": "OUTROS"
    },
    {
      "sentenca": "https://pje1g.trf1.jus.br:443/consultapublica/Processo/ConsultaDocumento/listView.seam?x=23091816304471000001796688347",
      "label": "OUTROS"
    },
    {
      "sentenca": "Número do documento: 23091816304471000001796688347Documento id 1821189655 - Sentença Tipo D",
      "label": "OUTROS"
    },
    {
      "sentenca": "A primeira testemunha de Defesa do sr. Edival, MICHAEL ROCHA DE ALMEIDA, disse que é agricultor.",
      "label": "FUNDAMENTACAO"
    },
    {
      "sentenca": "Já esteve na propriedade dos dois acusados, que não residem na propriedade.",
      "label": "FUNDAMENTACAO"
    },
    {
      "sentenca": "Eles moram na Agrovila, a 15 quilômetros.",
      "label": "FUNDAMENTACAO"
    },
    {
      "sentenca": "Nas propriedades do sr. Dirceu e do sr. Edival, a porteira não fica trancada e não há cadeado.",
      "label": "FUNDAMENTACAO"
    },
    {
      "sentenca": "Sobre contrato de empreitada na região, disse que é o que todos fazem, arrumam trabalhadores, empreitam um “pedação” e funciona assim.",
      "label": "FUNDAMENTACAO"
    },
    {
      "sentenca": "Entram em acordo, chamam um trabalhador para fazer o serviço.",
      "label": "FUNDAMENTACAO"
    },
    {
      "sentenca": "Com essa contratação, a alimentação fica por conta do trabalhador, que fica responsável por sua própria alimentação.",
      "label": "FUNDAMENTACAO"
    },
    {
      "sentenca": "Ele não precisa cumprir um horário de trabalho, he que manda, ele trabalha quando quiser e para na hora que quer.",
      "label": "FUNDAMENTACAO"
    },
    {
      "sentenca": "A segunda testemunha de Defesa do sr. Edival, EDIVALDO RODRIGUES CHAVES, disse que é agricultor.",
      "label": "FUNDAMENTACAO"
    },
    {
      "sentenca": "Relatou que conhece a propriedade do sr. Dirceu e a do sr. Edival, mora a 15 quilômetros, na Agrovila.",
      "label": "FUNDAMENTACAO"
    },
    {
      "sentenca": "Eles não residem na propriedade, residem na Agrovila.",
      "label": "FUNDAMENTACAO"
    },
    {
      "sentenca": "Sobre a porteira ficar fechada, trancada com cadeado, disse que não, não fica fechada sem circulação.",
      "label": "FUNDAMENTACAO"
    },
    {
      "sentenca": "Sobre transporte do Travessão para a Agrovila, sempre há carro que faça o transporte.",
      "label": "FUNDAMENTACAO"
    },
    {
      "sentenca": "Tem moto também que passa.",
      "label": "FUNDAMENTACAO"
    },
    {
      "sentenca": "É agricultar e disse que costumam contratar trabalhadores para serviço de empreitada, é acostumado a fazer.",
      "label": "FUNDAMENTACAO"
    },
    {
      "sentenca": "A empreitada é feita com o contratante mostrando o serviço a executar, fala com ele para dizer o preço, a pessoa dá o preço e, conforme o combinado, manda fazer.",
      "label": "FUNDAMENTACAO"
    },
    {
      "sentenca": "Sobre o contratado por empreitada, ele não cumpre horário, pois ele é como se fosse o dono do serviço, ele que faz o horário dele.",
      "label": "FUNDAMENTACAO"
    },
    {
      "sentenca": "O patrão não tem nada a ver, pois ele está na empreita.",
      "label": "FUNDAMENTACAO"
    },
    {
      "sentenca": "Sobre a alimentação deles, disse que é a primeira coisa que fala na contratação, tudo fica por conta dele, do trabalhador, já fala logo, que ele que coma à vontade do jeito dele.",
      "label": "FUNDAMENTACAO"
    },
    {
      "sentenca": "O depoente, arrolado como testemunha de defesa do sr. Dirceu, UDISON DOS SANTOS ANDRADE, disse que é agricultor.",
      "label": "FUNDAMENTACAO"
    },
    {
      "sentenca": "Disse que é amigo próximo do acusado, razão pela qual foi ouvido como informante.",
      "label": "FUNDAMENTACAO"
    },
    {
      "sentenca": "Disse que conhece as propriedades dos acusados, relatou que a propriedade fica aberta, com porteira encostada, mas aberta, sem cadeado, nem nada.",
      "label": "FUNDAMENTACAO"
    },
    {
      "sentenca": "Disse que é vizinho e que o costume da região para contratar serviço na região é por meio de empreita, é feita empreitada para o trabalhador fazer o trabalho.",
      "label": "FUNDAMENTACAO"
    },
    {
      "sentenca": "Disse que o trabalhador fará o serviço no momento e no dia em que ele quiser trabalhar, da maneira como ele quiser.",
      "label": "FUNDAMENTACAO"
    },
    {
      "sentenca": "Ele faz no momento em que vai, em que quer ir, não tem obrigação de trabalho.",
      "label": "FUNDAMENTACAO"
    },
    {
      "sentenca": "A alimentação pode ser pedida e ele diz qual tipo ele quer ou ele mesmo leva, ele tem disponibilidade de levar, é livre.",
      "label": "FUNDAMENTACAO"
    },
    {
      "sentenca": "Sobre conhecer os trabalhadores, José Maria, Zaqueu, Evânio, Luiz Carlos, disse que não conhece, vê trabalhando, mas não tem conhecimento direto com os trabalhadores.",
      "label": "FUNDAMENTACAO"
    },
    {
      "sentenca": "Vê trabalhando lá.",
      "label": "FUNDAMENTACAO"
    },
    {
      "sentenca": "Relata que, até onde sabe, eles foram contratados por empreitada.",
      "label": "FUNDAMENTACAO"
    },
    {
      "sentenca": "Disse que no Município de Medicilândia não há água tratada.",
      "label": "FUNDAMENTACAO"
    },
    {
      "sentenca": "O depoente, arrolado como testemunha de defesa do sr. Edival, MARCOS PEREIRA DE JESUS DE SOUZA, disse que é filho de Jovelina Pereira de Jesus de Souza e é agricultor.",
      "label": "FUNDAMENTACAO"
    },
    {
      "sentenca": "Disse que é amigo próximo do acusado, razão pela qual foi ouvido como informante.",
      "label": "FUNDAMENTACAO"
    },
    {
      "sentenca": "Relatou conhecer a propriedade do sr. Dirceu e do sr. Edival.",
      "label": "FUNDAMENTACAO"
    },
    {
      "sentenca": "Disse que a porteira da propriedade fica aberta.",
      "label": "FUNDAMENTACAO"
    },
    {
      "sentenca": "Sobre ter casa na propriedade, disse que sim, inclusive tem banheiro.",
      "label": "FUNDAMENTACAO"
    },
    {
      "sentenca": "Sobre o contrato de empreitada, disse que é mostrado o local do serviço, o que fazer, e então entram em combinação o dolo da propriedade e o empregado, vai da combinação.",
      "label": "FUNDAMENTACAO"
    },
    {
      "sentenca": "É por empreita.",
      "label": "FUNDAMENTACAO"
    },
    {
      "sentenca": "É por conta dos trabalhadores, depende deles, inclusive se cumprem ou não horário.",
      "label": "FUNDAMENTACAO"
    },
    {
      "sentenca": "O pagamento é uma questão de combinação, às vezes pedem um adiantamento para comprar mantimento para empreita, mas vai da combinação.",
      "label": "FUNDAMENTACAO"
    },
    {
      "sentenca": "A pessoa vai trabalhando e pega a empreita, assim vai.",
      "label": "FUNDAMENTACAO"
    },
    {
      "sentenca": "Sobre conhecer os trabalhadores encontrados no local, José Maria, Zaqueu, Ronaldo, Luiz Carlos, disse que não.",
      "label": "FUNDAMENTACAO"
    },
    {
      "sentenca": "Num. 1821189655 - Pág. 6",
      "label": "OUTROS"
    },
    {
      "sentenca": "Assinado eletronicamente por: MICHAEL PROCOPIO RIBEIRO ALVES AVELAR - 20/09/2023 15:22:25",
      "label": "OUTROS"
    },
    {
      "sentenca": "https://pje1g.trf1.jus.br:443/consultapublica/Processo/ConsultaDocumento/listView.seam?x=23091816304471000001796688347",
      "label": "OUTROS"
    },
    {
      "sentenca": "Número do documento: 23091816304471000001796688347Documento id 1821189655 - Sentença Tipo D",
      "label": "OUTROS"
    },
    {
      "sentenca": "Disse que não há água tratada em Medicilândia.",
      "label": "FUNDAMENTACAO"
    },
    {
      "sentenca": "Em seu interrogatório, DIRCEU DA LUZ, filho de Izolde Clara da Luz, disse que é agricultor, mas já foi funcionário público na Prefeitura de Medicilândia.",
      "label": "FUNDAMENTACAO"
    },
    {
      "sentenca": "Sua renda mensal média é de 2 ou 3 salários na Prefeitura, e anualmente retira uns R$ 30.000,00 da agricultura.",
      "label": "FUNDAMENTACAO"
    },
    {
      "sentenca": "É casado, tem uma filha menor de idade.",
      "label": "FUNDAMENTACAO"
    },
    {
      "sentenca": "Nunca foi preso nem processado anteriormente.",
      "label": "FUNDAMENTACAO"
    },
    {
      "sentenca": "Disse que está em Medicilância e os trabalhadores estão usando de má-fé com os proprietários, porque querem ir lá e depois denunciar, pegar dinheiro fácil e incriminar o proprietário, como ocorreu consigo.",
      "label": "FUNDAMENTACAO"
    },
    {
      "sentenca": "Mandou a chave do rapaz para a sua casa, que tem água encanada, geladeira, TV, tem tudo, mas não ficaram na casa.",
      "label": "FUNDAMENTACAO"
    },
    {
      "sentenca": "Foi autuado, a casa estava lá e está lá.",
      "label": "FUNDAMENTACAO"
    },
    {
      "sentenca": "O MP foi atrás deles, foram atrás da casa, fotografaram o que bem entenderam, mas não ouviram os proprietários, apenas os trabalhadores.",
      "label": "FUNDAMENTACAO"
    },
    {
      "sentenca": "Ele pegou a chave em sua mão e não entrou na chave.",
      "label": "FUNDAMENTACAO"
    },
    {
      "sentenca": "Falou para dra. Que a pessoa tinha a chave, mas ela falou que o problema era dele.",
      "label": "FUNDAMENTACAO"
    },
    {
      "sentenca": "Tem água de poço, encanada, a rodovia passa a 100 metros, tem livre acesso o dia todo e fim de semana.",
      "label": "FUNDAMENTACAO"
    },
    {
      "sentenca": "Eles saíam quando queriam, iam quando queriam.",
      "label": "FUNDAMENTACAO"
    },
    {
      "sentenca": "Nem mora lá, mora em Medicilândia e não poderia ir até lá dominá-los, mas não cortaram um pé lá.",
      "label": "FUNDAMENTACAO"
    },
    {
      "sentenca": "Ficaram lá e não trabalharam.",
      "label": "FUNDAMENTACAO"
    },
    {
      "sentenca": "Queria que o Ministério fosse lá para mostrar onde ele errou.",
      "label": "FUNDAMENTACAO"
    },
    {
      "sentenca": "Isso de serem escravos não tem na região, arrumaram a casa e eles trabalhavam na hora que eles querem e quando querem.",
      "label": "FUNDAMENTACAO"
    },
    {
      "sentenca": "Foi autuado e já queriam prender, estava com a consciência limpa, pois estava vendo o bem e o maior.",
      "label": "FUNDAMENTACAO"
    },
    {
      "sentenca": "Pediram para trabalhar, que estavam passando fome, estavam na rua, levou a pessoa para arrumar a vida dele e, quando pensa que não, a pessoa se depara com uma situação dessa.",
      "label": "FUNDAMENTACAO"
    },
    {
      "sentenca": "Podem conferir lá na propriedade dele, que está do mesmo jeito.",
      "label": "FUNDAMENTACAO"
    },
    {
      "sentenca": "Não precisa nem aumentar, nem diminuir.",
      "label": "FUNDAMENTACAO"
    },
    {
      "sentenca": "Não tinha CTPS assinada, ele nem tinha endereço fixo, chega lá dois dias e já sai.",
      "label": "FUNDAMENTACAO"
    },
    {
      "sentenca": "Disse que combinaram a empreita do serviço, sempre faz com negociação certa, e que o serviço de alimentação ficou por conta deles.",
      "label": "FUNDAMENTACAO"
    },
    {
      "sentenca": "Em seu interrogatório, EDIVAL DA LUZ, filho de Izolde Clara da Luz, disse que é casado.",
      "label": "FUNDAMENTACAO"
    },
    {
      "sentenca": "Não tem filhos menores.",
      "label": "FUNDAMENTACAO"
    },
    {
      "sentenca": "Sua renda mensal é do salário como professor, 4 ou 5 mil.",
      "label": "FUNDAMENTACAO"
    },
    {
      "sentenca": "Não trabalha mais com agricultura, ficou desanimado.",
      "label": "FUNDAMENTACAO"
    },
    {
      "sentenca": "Nunca foi preso nem processado anteriormente.",
      "label": "FUNDAMENTACAO"
    },
    {
      "sentenca": "Disse que o MP fez uma covardia muito grande, pois faz com que quem batalhou para ter honestidade e sempre ser honesto com as pessoas, inventa, não chama para dizer onde era a residência.",
      "label": "FUNDAMENTACAO"
    },
    {
      "sentenca": "Mostraram coisas que nem eram no seu lote.",
      "label": "FUNDAMENTACAO"
    },
    {
      "sentenca": "Disse que houve 3 trabalhadores que não ficaram 3 dias lá, não trabalhou 2 dias.",
      "label": "FUNDAMENTACAO"
    },
    {
      "sentenca": "O cara inventa uma história e, pior de tudo, quando está junto com a Dra., parece ser pior do que quem matou alguém.",
      "label": "FUNDAMENTACAO"
    },
    {
      "sentenca": "Quando foi jurado, o juiz tinha uma educação, achou que ela já era muito mal-educada, qualquer coisa ameaçava.",
      "label": "FUNDAMENTACAO"
    },
    {
      "sentenca": "Teve que pagar 5 mil, perguntou qual a lei e ela falou que era para servir de exemplo para os outros.",
      "label": "FUNDAMENTACAO"
    },
    {
      "sentenca": "Sentiu-se humilhado, enquanto o trabalhador fica pouco, volta e depois junta o período todo.",
      "label": "FUNDAMENTACAO"
    },
    {
      "sentenca": "O Ministério do Trabalho não acata nada e não deixa dar uma satisfação.",
      "label": "FUNDAMENTACAO"
    },
    {
      "sentenca": "Disse que ficou doente com isso.",
      "label": "FUNDAMENTACAO"
    },
    {
      "sentenca": "Ficou depressivo e não consegue dormir à noite.",
      "label": "FUNDAMENTACAO"
    },
    {
      "sentenca": "Colocaram tudo que não prestava em cima dele.",
      "label": "FUNDAMENTACAO"
    },
    {
      "sentenca": "Trabalha há 30 anos na escola, concursado, e os próprios alunos o conhecem, sabem como é ele.",
      "label": "FUNDAMENTACAO"
    },
    {
      "sentenca": "Podem depor, falar como ele é.",
      "label": "FUNDAMENTACAO"
    },
    {
      "sentenca": "O seu trabalhador tinha saído na sexta, vendeu uma moto para ele na sexta, pegou o dinheiro consigo e depois foram para outro travessão e não tinham voltado, foram pegar o cara lá e falaram que o cara estava em escravidão.",
      "label": "FUNDAMENTACAO"
    },
    {
      "sentenca": "E a dra. Falou que ele tinha que trabalhar oito horas e não entendeu, pois se falava que era trabalho escravo.",
      "label": "FUNDAMENTACAO"
    },
    {
      "sentenca": "Disse que inventam uma história e ele foi considerado mentiroso.",
      "label": "FUNDAMENTACAO"
    },
    {
      "sentenca": "Tem 56 anos e não esperava passar por isso, por algo que não fez.",
      "label": "FUNDAMENTACAO"
    },
    {
      "sentenca": "Relatou que chegaram em sua casa, no meio de uma vila em que morava, chegaram mais de 22 horas e queriam levá-lo à força, sua mãe passando mal e apontaram uma arma para ele.",
      "label": "FUNDAMENTACAO"
    },
    {
      "sentenca": "Sobre os trabalhadores mencionados na denúncia, disse que foram contratados por empreita, pediram um valor, já incluída a feira dos trabalhadores, e então pagava o valor que pediam.",
      "label": "FUNDAMENTACAO"
    },
    {
      "sentenca": "Num. 1821189655 - Pág. 7",
      "label": "OUTROS"
    },
    {
      "sentenca": "Assinado eletronicamente por: MICHAEL PROCOPIO RIBEIRO ALVES AVELAR - 20/09/2023 15:22:25",
      "label": "OUTROS"
    },
    {
      "sentenca": "https://pje1g.trf1.jus.br:443/consultapublica/Processo/ConsultaDocumento/listView.seam?x=23091816304471000001796688347",
      "label": "OUTROS"
    },
    {
      "sentenca": "Número do documento: 23091816304471000001796688347Documento id 1821189655 - Sentença Tipo D",
      "label": "OUTROS"
    },
    {
      "sentenca": "Terminava o pedaço e já pagava.",
      "label": "FUNDAMENTACAO"
    },
    {
      "sentenca": "Foram contratados para serviço de empreita.",
      "label": "FUNDAMENTACAO"
    },
    {
      "sentenca": "Sobre terem ficado no lote no período, José Maria, Zaqueu e EVânio, trabalharam por 2 dias, porque chegaram na quinta à noite, sujos, com cachaça, e foram lavar roupas, no dia seguinte e depois já teve domingo e na segunda chegou a fiscalização.",
      "label": "FUNDAMENTACAO"
    },
    {
      "sentenca": "Então, trabalhavam por um dia.",
      "label": "FUNDAMENTACAO"
    },
    {
      "sentenca": "O Luiz Carlos nem ficava lá.",
      "label": "FUNDAMENTACAO"
    },
    {
      "sentenca": "Eles geralmente fazem o pouco serviço que tem lá e vão trabalhando para os vizinhos, fazendo outros trabalhadores e quando o mato cresce eles voltam.",
      "label": "FUNDAMENTACAO"
    },
    {
      "sentenca": "Sobre o trabalhador chamado Ronaldo, questionado se trabalhou para o seu pai, disse que sim, mas a Dra. disse que ele deveria assumir porque era trabalhador do seu pai, que tinha falecido.",
      "label": "FUNDAMENTACAO"
    },
    {
      "sentenca": "Reside no Município de Medicilândia em dezembro de 1983.",
      "label": "FUNDAMENTACAO"
    },
    {
      "sentenca": "Disse que não tem água potável em Medicilândia, na água em que mora pegam da represa, onde o gado bebe, é essa que vai para a caixa.",
      "label": "FUNDAMENTACAO"
    },
    {
      "sentenca": "Sobre o termo de ajuste de conduta, firmado com o MPF, cumpriu corretamente.",
      "label": "FUNDAMENTACAO"
    },
    {
      "sentenca": "Portanto, não há dúvidas de que os trabalhadores resgatados exerciam suas atividades em condições degradantes, o que já é suficiente para caracterizar os elementos descritivos do tipo penal, a despeito da falta de provas de restrição da liberdade por dívida.",
      "label": "FUNDAMENTACAO"
    },
    {
      "sentenca": "Ainda que a restrição da liberdade não tenha sido cabalmente demonstrada nestes autos, vale lembrar que o delito, apesar de apresentar uma estrutura nuclear única, é de forma vinculada, ou melhor, de formas vinculadas, pois descreve várias condutas que configuram o \"reduzir à condição análoga à de escravo\", sendo a restrição de liberdade uma delas.",
      "label": "FUNDAMENTACAO"
    },
    {
      "sentenca": "De igual forma, doutrina e jurisprudência, inclusive o STJ, reconhecem não ser necessária a restrição à liberdade de locomoção para a configuração do delito.",
      "label": "FUNDAMENTACAO"
    },
    {
      "sentenca": "No que tange à autoria delitiva, os réus afirmaram que contrataram os trabalhadores na condição empreiteiros e negou o trabalho em condições degradantes.",
      "label": "FUNDAMENTACAO"
    },
    {
      "sentenca": "Com relação ao primeiro aspecto, penso não assistir razão à defesa, uma vez que os depoimentos prestados pelos trabalhadores em sede administrativa revelam que existia vínculo de subordinação, conforme relatório de fiscalização id. 227584017.",
      "label": "FUNDAMENTACAO"
    },
    {
      "sentenca": "Não é necessário que haja vínculo empregatício, podendo-se usar a nomenclatura de empreitada, diarista, boia-fria, desde que, de fato, haja uma vinculação dos indivíduos submetidos à condição degradante, como se nota de sua morada no local, ainda que, em alguns casos, tenha sido recente quando da fiscalização.",
      "label": "FUNDAMENTACAO"
    },
    {
      "sentenca": "A intenção de fixar morada demonstra a estabilidade do vínculo, o que é suficiente, ainda que a relação tenha sido, formalmente, indicada como um contrato de empreitada.",
      "label": "FUNDAMENTACAO"
    },
    {
      "sentenca": "No que tange ao segundo aspecto, igualmente não tem razão a defesa.",
      "label": "FUNDAMENTACAO"
    },
    {
      "sentenca": "Como demonstrado anteriormente, restou comprovado que os trabalhadores exerciam suas atividades em condições degradantes, as quais apresentam diversos elementos reforçando a situação indigna em que encontrados os trabalhadores, como ausência de instalações sanitárias e fornecimento de água.",
      "label": "FUNDAMENTACAO"
    },
    {
      "sentenca": "Assim, restou devidamente comprovado que os réus DIRCEU DA LUZ como incurso, por duas vezes e em concurso formal, na forma do artigo 70 do Código Penal, nos artigos 149, caput, 297, § 4º, todos do Código Penal, e EDIVAL DA LUZ como incurso, por cinco vezes, nos delitos do artigo 149 e 297, § 4º, na forma do artigo 69, todos do Código Penal.",
      "label": "FUNDAMENTACAO"
    },
    {
      "sentenca": "DO PEDIDO DE ABSOLVIÇÃO PELO MPF do delito dos Arts. 297, § 4º, CP, em razão da absorção pelo delito do Art. 149, CP.",
      "label": "FUNDAMENTACAO"
    },
    {
      "sentenca": "O MPF requereu a absorção do delito descrito no art. 297, § 4º, pelo art. 149, do CP.",
      "label": "FUNDAMENTACAO"
    },
    {
      "sentenca": "Num. 1821189655 - Pág. 8",
      "label": "OUTROS"
    },
    {
      "sentenca": "Assinado eletronicamente por: MICHAEL PROCOPIO RIBEIRO ALVES AVELAR - 20/09/2023 15:22:25",
      "label": "OUTROS"
    },
    {
      "sentenca": "https://pje1g.trf1.jus.br:443/consultapublica/Processo/ConsultaDocumento/listView.seam?x=23091816304471000001796688347",
      "label": "OUTROS"
    },
    {
      "sentenca": "Número do documento: 23091816304471000001796688347Documento id 1821189655 - Sentença Tipo D",
      "label": "OUTROS"
    },
    {
      "sentenca": "Nesta situação, denota-se que o delito do art. 297, § 4º, do CP constitui meio para a prática do crime mais grave, e o do art. 149 do CP, pressuposto básico para se falar em absorção de um delito pelo outro.",
      "label": "FUNDAMENTACAO"
    },
    {
      "sentenca": "Na hipótese, deve incidir o critério ou princípio da consunção, pois a ausência de anotação da CTPS é um meio necessário para o delito de trabalho escravo.",
      "label": "FUNDAMENTACAO"
    },
    {
      "sentenca": "O STJ no AgRg no REsp 1669730 / RJ, fixou a seguinte premissa: O princípio da consunção impõe que uma infração penal constitua, unicamente, ato preparatório, meio necessário ou fase da execução de outro fato descrito por norma mais ampla (crime-fim), de modo que o agente só responderá pelo delito mais grave, ficando o crime-meio será por ele absorvido.",
      "label": "FUNDAMENTACAO"
    },
    {
      "sentenca": "Nessa caminho, a omissão nas anotações da CTPS é um meio necessário ou, ao menos, um crime meio, para a prática do delito de redução à condição análoga de escravo.",
      "label": "FUNDAMENTACAO"
    },
    {
      "sentenca": "Dessa forma, impõe-se a absolvição dos réus em relação ao delito descrito no art. 297, § 4º, CP.",
      "label": "FUNDAMENTACAO"
    },
    {
      "sentenca": "3-DISPOSITIVO",
      "label": "DISPOSITIVO"
    },
    {
      "sentenca": "Ante o exposto, JULGO PARCIALMENTE PROCEDENTE a pretensão acusatória para:",
      "label": "DISPOSITIVO"
    },
    {
      "sentenca": "1- Condenar DIRCEU DA LUZ como incurso, por duas vezes e em concurso formal, na forma do artigo 70 do Código Penal, nos artigos 149, caput, Código Penal, e EDIVAL DA LUZ como incurso, por cinco vezes, nos delitos do artigo 149 na forma do artigo 70, todos do Código Penal;",
      "label": "DISPOSITIVO"
    },
    {
      "sentenca": "2- Absolver os réus dos delitos dos Art. 297, § 4º, com base no art. 386, VII, CPP.",
      "label": "DISPOSITIVO"
    },
    {
      "sentenca": "Passo a dosar as penas.",
      "label": "DOSIMETRIA"
    },
    {
      "sentenca": "Em atenção ao que determina o art. 59 do Código Penal, passo à dosimetria da pena do réu DIRCEU DA LUZ.",
      "label": "DOSIMETRIA"
    },
    {
      "sentenca": "Quanto ao crime do tipificado no art. 149 do CP, a culpabilidade se revela acima do comum, por envolver vários elementos degradantes, nem todos necessários para a configuração do delito.",
      "label": "DOSIMETRIA"
    },
    {
      "sentenca": "Não possui registro de maus antecedentes; conduta social aparentemente dentro da normalidade;",
      "label": "DOSIMETRIA"
    },
    {
      "sentenca": "a personalidade não pode ser aquilatada pelos elementos constantes dos autos;",
      "label": "DOSIMETRIA"
    },
    {
      "sentenca": "os motivos e circunstâncias e consequências do crime são inerentes à espécie; não há falar no caso em comportamento da vítima.",
      "label": "DOSIMETRIA"
    },
    {
      "sentenca": "Assim, fixo a sua pena base em 02 (dois) anos e 6 (seis) meses de reclusão e 10 (dez) dias-multa.",
      "label": "DOSIMETRIA"
    },
    {
      "sentenca": "Num. 1821189655 - Pág. 9",
      "label": "OUTROS"
    },
    {
      "sentenca": "Assinado eletronicamente por: MICHAEL PROCOPIO RIBEIRO ALVES AVELAR - 20/09/2023 15:22:25",
      "label": "OUTROS"
    },
    {
      "sentenca": "https://pje1g.trf1.jus.br:443/consultapublica/Processo/ConsultaDocumento/listView.seam?x=23091816304471000001796688347",
      "label": "OUTROS"
    },
    {
      "sentenca": "Número do documento: 23091816304471000001796688347Documento id 1821189655 - Sentença Tipo D",
      "label": "OUTROS"
    },
    {
      "sentenca": "Não há circunstâncias agravantes e nem atenuantes, porquanto deixo de reconhecer atenuante da confissão, visto que o réu não admitiu a prática delitiva e não há que se falar em confissão qualificada, além do mais a pena base ficou no limite, encontrando óbice na súmula 231, STJ.",
      "label": "DOSIMETRIA"
    },
    {
      "sentenca": "Não existem causas de diminuição ou aumento da pena, portanto fixo em definitiva a pena em 2 (dois) anos e 6 (seis) meses de reclusão e 10 (dez) dias-multa.",
      "label": "DOSIMETRIA"
    },
    {
      "sentenca": "Quanto à multa, considerando a condição econômica do réu, que declarou possuir renda de R$ 30.000,00, fixo cada dia-multa no valor correspondente a 1 (um) salário mínimo vigente à época do fato (2019), consoante dispõe o art. 49, § 1º, observado, ainda o disposto no art. 60, ambos do Código Penal.",
      "label": "DOSIMETRIA"
    },
    {
      "sentenca": "Em razão do reconhecimento do concurso formal, e nos termos da súmula 659 do STJ, para o aumento da pena pelo concurso formal dentre o intervalo de 1/6 (um sexto) a 1/2 (metade), previsto no art. 70 do Código Penal, deve-se adotar o critério da quantidade de infrações praticadas.",
      "label": "DOSIMETRIA"
    },
    {
      "sentenca": "Na espécie, trata-se de um total de 2 (duas) infrações penais, razão pela qual majoro a pena em 1/6, fixando a pena privativa de liberdade em 2 (dois) anos e 11 (onze) meses de reclusão, além do pagamento de multa em 15 (quinze) dias-multa.",
      "label": "DOSIMETRIA"
    },
    {
      "sentenca": "Uma vez que a pena supera não supera os 4 anos de reclusão e em face do disposto no art. 44, incisos I e III, e § 2º, segunda parte, c/c o art. 45, § 1º, e art. 46, todos do Código Penal, e ainda considerando os motivos que levaram à fixação da pena, preenchendo o réu os requisitos do art. 44 do CP, não havendo motivo suficiente para deixar de proceder à substituição, concedo-lhe esse benefício, substituindo a pena privativa de liberdade por duas restritivas de direito:",
      "label": "DOSIMETRIA"
    },
    {
      "sentenca": "a) prestação pecuniária, que, tendo em vista o valor do dano, é fixada em R$ 30.000,00 (trinta mil reais), valor da multa, cabendo ao réu providenciar o depósito na conta do juízo, conta judicial 0551.005.86400753-9;",
      "label": "DOSIMETRIA"
    },
    {
      "sentenca": "b) prestação de serviços à comunidade, correspondente a uma hora de tarefa por dia de condenação, na forma do artigo 46, § 3º, do CP, em local a ser indicado pelo juízo da execução penal.",
      "label": "DOSIMETRIA"
    },
    {
      "sentenca": "O regime inicial de cumprimento de pena é o aberto, considerando o quantum da pena aplicada, nos termos do artigo 33, § 2º, alínea c, do CP.",
      "label": "DOSIMETRIA"
    },
    {
      "sentenca": "Sem aplicação do Art. 77, do CP.",
      "label": "DOSIMETRIA"
    },
    {
      "sentenca": "Em atenção ao que determina o art. 59 do Código Penal, passo à dosimetria da pena do réu EDIVAL DA LUZ.",
      "label": "DOSIMETRIA"
    },
    {
      "sentenca": "Quanto ao crime do tipificado no art. 149 do CP, a culpabilidade se revela acima do comum, por envolver vários elementos degradantes, nem todos necessários para a configuração do delito.",
      "label": "DOSIMETRIA"
    },
    {
      "sentenca": "Não possui registro de maus antecedentes; conduta social aparentemente dentro da normalidade;",
      "label": "DOSIMETRIA"
    },
    {
      "sentenca": "Num. 1821189655 - Pág. 10",
      "label": "OUTROS"
    },
    {
      "sentenca": "Assinado eletronicamente por: MICHAEL PROCOPIO RIBEIRO ALVES AVELAR - 20/09/2023 15:22:25",
      "label": "OUTROS"
    },
    {
      "sentenca": "https://pje1g.trf1.jus.br:443/consultapublica/Processo/ConsultaDocumento/listView.seam?x=23091816304471000001796688347",
      "label": "OUTROS"
    },
    {
      "sentenca": "Número do documento: 23091816304471000001796688347Documento id 1821189655 - Sentença Tipo D",
      "label": "OUTROS"
    },
    {
      "sentenca": "a personalidade não pode ser aquilatada pelos elementos constantes dos autos;",
      "label": "DOSIMETRIA"
    },
    {
      "sentenca": "os motivos e circunstâncias e consequências do crime são inerentes à espécie; não há falar no caso em comportamento da vítima.",
      "label": "DOSIMETRIA"
    },
    {
      "sentenca": "Assim, fixo a sua pena base em 02 (dois) anos e 6 (seis) meses de reclusão e 10 (dez) dias-multa.",
      "label": "DOSIMETRIA"
    },
    {
      "sentenca": "Não há circunstâncias agravantes e nem atenuantes, porquanto deixo de reconhecer atenuante da confissão, visto que o réu não admitiu a prática delitiva e não há que se falar em confissão qualificada, além disso, a pena base ficou no limite, encontrando óbice na súmula 231, STJ.",
      "label": "DOSIMETRIA"
    },
    {
      "sentenca": "Não existem causas de diminuição ou aumento da pena, portanto fixo em definitiva a pena em 2 (dois) anos e 6 (seis) meses de reclusão e 10 (dez) dias-multa.",
      "label": "DOSIMETRIA"
    },
    {
      "sentenca": "Quanto à multa, considerando a condição econômica do réu, que declarou possuir renda de R$ 5.000,00, fixo cada dia-multa no valor correspondente a 1/6 (um sexto) salário mínimo vigente à época do fato (2019), consoante dispõe o art. 49, § 1º, observado, ainda o disposto no art. 60, ambos do Código Penal.",
      "label": "DOSIMETRIA"
    },
    {
      "sentenca": "Em razão do reconhecimento do concurso formal, e nos termos da súmula 659 do STJ, para o aumento da pena pelo concurso formal dentre o intervalo de 1/6 (um sexto) a 1/2 (metade), previsto no art. 70 do Código Penal, deve-se adotar o critério da quantidade de infrações praticadas.",
      "label": "DOSIMETRIA"
    },
    {
      "sentenca": "Na espécie, trata-se de um total de 5 (cinco) infrações penais, razão pela qual majoro a pena em 1/3, fixando a pena privativa de liberdade em 3 (três) anos e 4 (quatro) meses de reclusão e o pagamento de multa em 20 (vinte) dias-multa.",
      "label": "DOSIMETRIA"
    },
    {
      "sentenca": "Uma vez que a pena supera não supera os 4 anos de reclusão e em face do disposto no art. 44, incisos I e III, e § 2º, segunda parte, c/c o art. 45, § 1º, e art. 46, todos do Código Penal, e ainda considerando os motivos que levaram à fixação da pena, preenchendo o réu os requisitos do art. 44 do CP, não havendo motivo suficiente para deixar de proceder à substituição, concedo-lhe esse benefício, substituindo a pena privativa de liberdade por duas restritivas de direito:",
      "label": "DOSIMETRIA"
    },
    {
      "sentenca": "a) prestação pecuniária, que, tendo em vista o valor do dano, é fixada em R$ 10.000,00 (dez mil reais), valor da multa, cabendo ao réu providenciar o depósito na conta do juízo, conta judicial 0551.005.86400753-9;",
      "label": "DOSIMETRIA"
    },
    {
      "sentenca": "b) prestação de serviços à comunidade, correspondente a uma hora de tarefa por dia de condenação, na forma do artigo 46, § 3º, do CP, em local a ser indicado pelo juízo da execução penal.",
      "label": "DOSIMETRIA"
    },
    {
      "sentenca": "O regime inicial de cumprimento de pena é o aberto, considerando o quantum da pena aplicada, nos termos do artigo 33, § 2º, alínea c, do CP.",
      "label": "DOSIMETRIA"
    },
    {
      "sentenca": "Sem aplicação do Art. 77, do CP.",
      "label": "DOSIMETRIA"
    },
    {
      "sentenca": "Deixo de fixar o valor mínimo para reparação dos danos, prevista no art. 387, IV, do CPP, em razão da ausência de pedido neste sentido por parte do Ministério Público Federal ou pela União, bem como da ausência de contraditório a respeito.",
      "label": "DISPOSITIVO"
    },
    {
      "sentenca": "Num. 1821189655 - Pág. 11",
      "label": "OUTROS"
    },
    {
      "sentenca": "Assinado eletronicamente por: MICHAEL PROCOPIO RIBEIRO ALVES AVELAR - 20/09/2023 15:22:25",
      "label": "OUTROS"
    },
    {
      "sentenca": "https://pje1g.trf1.jus.br:443/consultapublica/Processo/ConsultaDocumento/listView.seam?x=23091816304471000001796688347",
      "label": "OUTROS"
    },
    {
      "sentenca": "Número do documento: 23091816304471000001796688347Documento id 1821189655 - Sentença Tipo D",
      "label": "OUTROS"
    },
    {
      "sentenca": "Do direito de apelar em liberdade",
      "label": "DISPOSITIVO"
    },
    {
      "sentenca": "Considerando que os réus permaneceram em liberdade durante toda a instrução, o montante da pena aplicada e o regime inicial de seu cumprimento, bem como a ausência de qualquer circunstância justificadora de sua segregação preventiva, devem permanecer em liberdade.",
      "label": "DISPOSITIVO"
    },
    {
      "sentenca": "Com fundamento no art. 804 do Código de Processo Penal e no art. 6º da Lei nº 9.289/1996, condeno os réus ao pagamento das custas.",
      "label": "DISPOSITIVO"
    },
    {
      "sentenca": "Após o trânsito em julgado: a) comunique-se à autoridade policial e ao Tribunal Regional Eleitoral, para os fins do artigo 15, III, da Constituição Federal; c) oficie-se ao órgão de estatística, para os fins do artigo 809 do CPP..",
      "label": "DISPOSITIVO"
    },
    {
      "sentenca": "Promovam-se as diligências necessárias.",
      "label": "DISPOSITIVO"
    },
    {
      "sentenca": "Intimem-se.",
      "label": "DISPOSITIVO"
    },
    {
      "sentenca": "Altamira/PA, 20 de setembro de 2023.",
      "label": "OUTROS"
    },
    {
      "sentenca": "(assinado digitalmente)",
      "label": "OUTROS"
    },
    {
      "sentenca": "MICHAEL PROCOPIO RIBEIRO ALVES AVELAR",
      "label": "OUTROS"
    },
    {
      "sentenca": "JUIZ FEDERAL",
      "label": "OUTROS"
    },
    {
      "sentenca": "Num. 1821189655 - Pág. 12",
      "label": "OUTROS"
    },
    {
      "sentenca": "Assinado eletronicamente por: MICHAEL PROCOPIO RIBEIRO ALVES AVELAR - 20/09/2023 15:22:25",
      "label": "OUTROS"
    },
    {
      "sentenca": "https://pje1g.trf1.jus.br:443/consultapublica/Processo/ConsultaDocumento/listView.seam?x=23091816304471000001796688347",
      "label": "OUTROS"
    },
    {
      "sentenca": "Número do documento: 23091816304471000001796688347",
      "label": "OUTROS"
    }
  ]
}